webfs/__init__.py
webfs/webfs.py
webfs-0.0.3.dist-info/METADATA
webfs-0.0.3.dist-info/WHEEL
webfs-0.0.3.dist-info/top_level.txt
webfs-0.0.3.dist-info/RECORD
