Metadata-Version: 2.1
Name: webfs
Version: 0.0.3
Summary: A filesystem for the web
Author-email: Jason Wilkes <notarealdeveloper@gmail.com>
Project-URL: source, https://github.com/notarealdeveloper/webfs
Project-URL: download, https://pypi.org/project/webfs/#files
Requires-Dist: bs4
Requires-Dist: mmry
Requires-Dist: colorama
Requires-Dist: requests
